MANIFEST.in
README.markdown
dev-requirements.txt
requirements.txt
setup.py
vip/__init__.py
vip/core.py
vip/main.py
vip.egg-info/PKG-INFO
vip.egg-info/SOURCES.txt
vip.egg-info/dependency_links.txt
vip.egg-info/entry_points.txt
vip.egg-info/not-zip-safe
vip.egg-info/requires.txt
vip.egg-info/top_level.txt
vip/test/__init__.py
vip/test/test_core.py
vip/test/test_helper.py
vip/test/test_main.py