Metadata-Version: 1.1
Name: vip
Version: 0.1.3
Summary: vip is a simple library that makes your python aware of existing virtualenv underneath.
Home-page: https://github.com/dejw/vip/
Author: Dawid Fatyga
Author-email: dawid.fatyga@gmail.com
License: BSD
Platform: any
Classifier: Development Status :: 1 - Planning
Classifier: Intended Audience :: Developers
Classifier: Intended Audience :: End Users/Desktop
Classifier: Intended Audience :: Information Technology
Classifier: Intended Audience :: Science/Research
Classifier: Intended Audience :: System Administrators
Classifier: License :: OSI Approved :: BSD License
Classifier: Operating System :: POSIX
Classifier: Operating System :: MacOS
Classifier: Operating System :: Unix
Classifier: Programming Language :: Python
Classifier: Topic :: System :: Systems Administration
Classifier: Topic :: Utilities
